{"count": 192, "ilvl": {"min": 728.3, "max": 729.6, "avg": 729.0}, "avgStats": {"haste": 23678, "crit": 19162, "mastery": 3962, "versatility": 17776, "strength": 10767.0, "agility": 98848.0, "intellect": 14479.0, "stamina": 792351.0}, "primaryStat": "agility", "statsSource": "gear_stats", "allSlots": {"head": [{"item": {"itemId": 237646, "itemName": "Клобук вестника полуночи", "iconName": "inv_helm_mail_raidhunterethereal_d_01", "quality": "epic", "itemLevel": 730, "bonusIds": ["1540", "6652", "10255", "10356", "12231", "12365", "12676", "13446"], "fullItemUrl": "https://www.wowhead.com/ru/item=237646?bonus=1540:6652:10255:10356:12231:12365:12676:13446&ilvl=730"}, "count": 176, "pct": 0.9166666666666666}], "neck": [{"item": {"itemId": 237568, "itemName": "Хризалида разлученных душ", "iconName": "inv_112_raidtrinkets_necklace01_etherealnontechnologicalstyle_gold", "quality": "epic", "itemLevel": 730, "bonusIds": ["1540", "6652", "10255", "10356", "10396", "10879", "13446"], "fullItemUrl": "https://www.wowhead.com/ru/item=237568?bonus=1540:6652:10255:10356:10396:10879:13446&ilvl=730"}, "count": 104, "pct": 0.5416666666666666}, {"item": {"itemId": 252009, "itemName": "Окровавленный сувенир", "iconName": "inv_11_0_arathor_necklace_01_color1", "quality": "epic", "itemLevel": 730, "bonusIds": ["1579", "6652", "10255", "10383", "10390", "10396", "10879", "13446"], "fullItemUrl": "https://www.wowhead.com/ru/item=252009?bonus=1579:6652:10255:10383:10390:10396:10879:13446&ilvl=730"}, "count": 28, "pct": 0.14583333333333334}], "shoulder": [{"item": {"itemId": 237644, "itemName": "Щитки теней вестника полуночи", "iconName": "inv_shoulder_mail_raidhunterethereal_d_01", "quality": "epic", "itemLevel": 730, "bonusIds": ["1540", "6652", "10255", "10356", "12233", "12675", "13446"], "fullItemUrl": "https://www.wowhead.com/ru/item=237644?bonus=1540:6652:10255:10356:12233:12675:13446&ilvl=730"}, "count": 179, "pct": 0.9322916666666666}], "back": [{"item": {"itemId": 235499, "itemName": "Повязки реши", "iconName": "inv_cape_armor_etherealshawl_d_01", "quality": "epic", "itemLevel": 730, "bonusIds": ["9893", "12259", "12401"], "fullItemUrl": "https://www.wowhead.com/ru/item=235499?bonus=9893:12259:12401&ilvl=730"}, "count": 192, "pct": 1.0}], "chest": [{"item": {"itemId": 237649, "itemName": "Хауберк вестника полуночи", "iconName": "inv_chest_mail_raidhunterethereal_d_01", "quality": "epic", "itemLevel": 730, "bonusIds": ["1540", "6652", "10255", "10356", "12229", "12676", "13446"], "fullItemUrl": "https://www.wowhead.com/ru/item=237649?bonus=1540:6652:10255:10356:12229:12676:13446&ilvl=730"}, "count": 186, "pct": 0.96875}], "wrist": [{"item": {"itemId": 219342, "itemName": "Гравированные символами тяжелые наручи", "iconName": "inv_mail_outdoorarathor_d_01_bracer", "quality": "epic", "itemLevel": 727, "bonusIds": ["8795", "8902", "8960", "9627", "9633", "10421", "11303", "12050", "12053", "12922", "13468"], "fullItemUrl": "https://www.wowhead.com/ru/item=219342?bonus=8795:8902:8960:9627:9633:10421:11303:12050:12053:12922:13468&ilvl=727"}, "count": 180, "pct": 0.9375}], "hands": [{"item": {"itemId": 237647, "itemName": "Перчатки вестника полуночи", "iconName": "inv_glove_mail_raidhunterethereal_d_01", "quality": "epic", "itemLevel": 730, "bonusIds": ["1540", "6652", "10255", "10356", "12230", "12675", "13446"], "fullItemUrl": "https://www.wowhead.com/ru/item=237647?bonus=1540:6652:10255:10356:12230:12675:13446&ilvl=730"}, "count": 158, "pct": 0.8229166666666666}], "waist": [{"item": {"itemId": 219339, "itemName": "Гравированная символами обвязка", "iconName": "inv_mail_outdoorarathor_d_01_belt", "quality": "epic", "itemLevel": 727, "bonusIds": ["8795", "8902", "8960", "9627", "9633", "10421", "11303", "12050", "12053", "12922", "13468"], "fullItemUrl": "https://www.wowhead.com/ru/item=219339?bonus=8795:8902:8960:9627:9633:10421:11303:12050:12053:12922:13468&ilvl=727"}, "count": 142, "pct": 0.7395833333333334}, {"item": {"itemId": 237522, "itemName": "Колоссальные узы жизни", "iconName": "inv_belt_mail_raidhunterethereal_d_01", "quality": "epic", "itemLevel": 730, "bonusIds": ["1540", "6652", "10255", "10356", "12239", "12365", "13446"], "fullItemUrl": "https://www.wowhead.com/ru/item=237522?bonus=1540:6652:10255:10356:12239:12365:13446&ilvl=730"}, "count": 17, "pct": 0.08854166666666667}], "legs": [{"item": {"itemId": 238032, "itemName": "Усиленные поножи послушника", "iconName": "inv_pant_mail_raidevokerethereal_d_01", "quality": "epic", "itemLevel": 730, "bonusIds": ["1540", "6652", "10255", "10356", "10844", "12239", "13446"], "fullItemUrl": "https://www.wowhead.com/ru/item=238032?bonus=1540:6652:10255:10356:10844:12239:13446&ilvl=730"}, "count": 100, "pct": 0.5208333333333334}, {"item": {"itemId": 237645, "itemName": "Фалды вестника полуночи", "iconName": "inv_pant_mail_raidhunterethereal_d_01", "quality": "epic", "itemLevel": 730, "bonusIds": ["1540", "10255", "10356", "12232", "12676", "13446"], "fullItemUrl": "https://www.wowhead.com/ru/item=237645?bonus=1540:10255:10356:12232:12676:13446&ilvl=730"}, "count": 42, "pct": 0.21875}], "feet": [{"item": {"itemId": 243308, "itemName": "Плетеные сапоги захватчика", "iconName": "inv_boot_mail_raidshamanethereal_d_01", "quality": "epic", "itemLevel": 730, "bonusIds": ["1540", "6652", "10255", "10356", "12239", "13446", "13504"], "fullItemUrl": "https://www.wowhead.com/ru/item=243308?bonus=1540:6652:10255:10356:12239:13446:13504&ilvl=730"}, "count": 190, "pct": 0.9895833333333334}], "finger1": [{"item": {"itemId": 242405, "itemName": "Перстень расколотой души", "iconName": "inv_112_raidtrinkets_ring02_etherealribbonorrunestyle_gold", "quality": "epic", "itemLevel": 730, "bonusIds": ["1540", "6652", "10255", "10356", "10396", "10879", "13446"], "fullItemUrl": "https://www.wowhead.com/ru/item=242405?bonus=1540:6652:10255:10356:10396:10879:13446&ilvl=730"}, "count": 47, "pct": 0.24479166666666666}, {"item": {"itemId": 246281, "itemName": "Кольцо паноплии", "iconName": "inv_misc_60raid_ring_1b", "quality": "epic", "itemLevel": 730, "bonusIds": ["6652", "10042", "10255", "10383", "10390", "10396", "10879", "13446"], "fullItemUrl": "https://www.wowhead.com/ru/item=246281?bonus=6652:10042:10255:10383:10390:10396:10879:13446&ilvl=730"}, "count": 7, "pct": 0.036458333333333336}], "finger2": [{"item": {"itemId": 242405, "itemName": "Перстень расколотой души", "iconName": "inv_112_raidtrinkets_ring02_etherealribbonorrunestyle_gold", "quality": "epic", "itemLevel": 730, "bonusIds": ["1540", "6652", "10255", "10356", "10396", "10879", "13446"], "fullItemUrl": "https://www.wowhead.com/ru/item=242405?bonus=1540:6652:10255:10356:10396:10879:13446&ilvl=730"}, "count": 48, "pct": 0.25}, {"item": {"itemId": 185813, "itemName": "Печатка взрывающихся звезд", "iconName": "inv_jewelcrafting_80_maxlvlring_blue", "quality": "epic", "itemLevel": 730, "bonusIds": ["6652", "10042", "10255", "10383", "10390", "10396", "10879", "13446"], "fullItemUrl": "https://www.wowhead.com/ru/item=185813?bonus=6652:10042:10255:10383:10390:10396:10879:13446&ilvl=730"}, "count": 17, "pct": 0.08854166666666667}]}, "weapon": [{"item": {"itemId": 185783, "itemName": "Язам Сокрушитель", "iconName": "inv_crossbow_2h_broker_c_01", "quality": "epic", "itemLevel": 730, "bonusIds": ["6652", "10042", "10255", "10384", "10390", "13446"], "fullItemUrl": "https://www.wowhead.com/ru/item=185783?bonus=6652:10042:10255:10384:10390:13446&ilvl=730"}, "count": 157, "pct": 0.8177083333333334}, {"item": {"itemId": 237733, "itemName": "Израненный заклинатель потока", "iconName": "inv_crossbow_2h_etherealraid_d_01", "quality": "epic", "itemLevel": 730, "bonusIds": ["1540", "6652", "10255", "10356", "13446"], "fullItemUrl": "https://www.wowhead.com/ru/item=237733?bonus=1540:6652:10255:10356:13446&ilvl=730"}, "count": 13, "pct": 0.06770833333333333}, {"item": {"itemId": 237732, "itemName": "Пронзающий нитяной лук", "iconName": "inv_bow_1h_etherealraid_d_01", "quality": "epic", "itemLevel": 730, "bonusIds": ["1540", "6652", "10255", "10356", "13446"], "fullItemUrl": "https://www.wowhead.com/ru/item=237732?bonus=1540:6652:10255:10356:13446&ilvl=730"}, "count": 7, "pct": 0.036458333333333336}, {"item": {"itemId": 242476, "itemName": "Пустынный карабин Таа'бата", "iconName": "inv_-firearm_2h_outdoorethereal_c_01", "quality": "epic", "itemLevel": 730, "bonusIds": ["3222", "10255", "10384", "10390", "13446"], "fullItemUrl": "https://www.wowhead.com/ru/item=242476?bonus=3222:10255:10384:10390:13446&ilvl=730"}, "count": 2, "pct": 0.010416666666666666}, {"item": {"itemId": 234492, "itemName": "БББФГ Кизы для Б", "iconName": "inv_firearm_2h_outdoorundermine_c_01", "quality": "epic", "itemLevel": 730, "bonusIds": ["1579", "6652", "10255", "10384", "10390", "13446"], "fullItemUrl": "https://www.wowhead.com/ru/item=234492?bonus=1579:6652:10255:10384:10390:13446&ilvl=730"}, "count": 2, "pct": 0.010416666666666666}], "offHand": [], "trinkets": [{"item": {"itemId": 242396, "itemName": "Незыблемая призма Пустоты", "iconName": "inv_112_raidtrinkets_voidprism", "quality": "epic", "itemLevel": 730, "bonusIds": ["1540", "6652", "10255", "10356", "13446"], "fullItemUrl": "https://www.wowhead.com/ru/item=242396?bonus=1540:6652:10255:10356:13446&ilvl=730"}, "count": 191, "pct": 0.9947916666666666}, {"item": {"itemId": 242402, "itemName": "Ритуальный горн Араза", "iconName": "inv_112_raidtrinkets_trinkettechnomancer_ritualengine", "quality": "epic", "itemLevel": 730, "bonusIds": ["1540", "6652", "10255", "10356", "13446"], "fullItemUrl": "https://www.wowhead.com/ru/item=242402?bonus=1540:6652:10255:10356:13446&ilvl=730"}, "count": 185, "pct": 0.9635416666666666}, {"item": {"itemId": 242395, "itemName": "Астральный усик", "iconName": "inv_112_raidtrinkets_silkwormsantenna", "quality": "epic", "itemLevel": 730, "bonusIds": ["1540", "6652", "10255", "10356", "13446"], "fullItemUrl": "https://www.wowhead.com/ru/item=242395?bonus=1540:6652:10255:10356:13446&ilvl=730"}, "count": 7, "pct": 0.036458333333333336}, {"item": {"itemId": 219314, "itemName": "Кокон выводка Ара-Кары", "iconName": "inv_raid_mercurialegg_red", "quality": "epic", "itemLevel": 730, "bonusIds": ["3222", "6652", "10255", "10383", "10390", "13446"], "fullItemUrl": "https://www.wowhead.com/ru/item=219314?bonus=3222:6652:10255:10383:10390:13446&ilvl=730"}, "count": 1, "pct": 0.005208333333333333}], "tierStats": [{"slot": "Голова", "slotKey": "head", "pct": 0.9947916666666666, "item": {"itemId": 237646, "itemName": "Клобук вестника полуночи", "iconName": "inv_helm_mail_raidhunterethereal_d_01", "quality": "epic", "itemLevel": 730, "bonusIds": ["1540", "6652", "10255", "10356", "12231", "12365", "12676", "13446"], "fullItemUrl": "https://www.wowhead.com/ru/item=237646?bonus=1540:6652:10255:10356:12231:12365:12676:13446&ilvl=730"}}, {"slot": "Грудь", "slotKey": "chest", "pct": 0.9791666666666666, "item": {"itemId": 237649, "itemName": "Хауберк вестника полуночи", "iconName": "inv_chest_mail_raidhunterethereal_d_01", "quality": "epic", "itemLevel": 730, "bonusIds": ["1540", "6652", "10255", "10356", "12229", "12676", "13446"], "fullItemUrl": "https://www.wowhead.com/ru/item=237649?bonus=1540:6652:10255:10356:12229:12676:13446&ilvl=730"}}, {"slot": "Плечи", "slotKey": "shoulder", "pct": 0.9583333333333334, "item": {"itemId": 237644, "itemName": "Щитки теней вестника полуночи", "iconName": "inv_shoulder_mail_raidhunterethereal_d_01", "quality": "epic", "itemLevel": 730, "bonusIds": ["1540", "6652", "10255", "10356", "12233", "12675", "13446"], "fullItemUrl": "https://www.wowhead.com/ru/item=237644?bonus=1540:6652:10255:10356:12233:12675:13446&ilvl=730"}}, {"slot": "Руки", "slotKey": "hands", "pct": 0.875, "item": {"itemId": 237647, "itemName": "Перчатки вестника полуночи", "iconName": "inv_glove_mail_raidhunterethereal_d_01", "quality": "epic", "itemLevel": 730, "bonusIds": ["1540", "6652", "10255", "10356", "12230", "12675", "13446"], "fullItemUrl": "https://www.wowhead.com/ru/item=237647?bonus=1540:6652:10255:10356:12230:12675:13446&ilvl=730"}}, {"slot": "Ноги", "slotKey": "legs", "pct": 0.3020833333333333, "item": {"itemId": 237645, "itemName": "Фалды вестника полуночи", "iconName": "inv_pant_mail_raidhunterethereal_d_01", "quality": "epic", "itemLevel": 730, "bonusIds": ["1540", "10255", "10356", "12232", "12676", "13446"], "fullItemUrl": "https://www.wowhead.com/ru/item=237645?bonus=1540:10255:10356:12232:12676:13446&ilvl=730"}}], "enchants": [{"slot": "Back", "name": "Песнь крылатой грации", "spellId": "445386", "pct": 0.984375}, {"slot": "Back", "name": "Песнь клыков и самоисцеления", "spellId": "445393", "pct": 0.015625}, {"slot": "Chest", "name": "Кристаллическое сияние", "spellId": "445333", "pct": 1.0}, {"slot": "Wrist", "name": "Песнь брони и избежания", "spellId": "445334", "pct": 0.984375}, {"slot": "Wrist", "name": "Песнь брони и самоисцеления", "spellId": "445325", "pct": 0.015625}, {"slot": "Legs", "name": "Усиленные штормом накладки", "spellId": "451825", "pct": 0.9739583333333334}, {"slot": "Legs", "name": "Накладки защитника", "spellId": "451828", "pct": 0.026041666666666668}, {"slot": "Feet", "name": "Ход защитника", "spellId": "445396", "pct": 0.84375}, {"slot": "Feet", "name": "Ход разведчика", "spellId": "445368", "pct": 0.15625}, {"slot": "Main_hand", "name": "Упорство Присягнувших", "spellId": "445351", "pct": 0.5833333333333334}, {"slot": "Main_hand", "name": "Хитрость Совета", "spellId": "445379", "pct": 0.3854166666666667}, {"slot": "Finger1", "name": "Сияющая универсальность", "spellId": "445349", "pct": 0.3958333333333333}, {"slot": "Finger1", "name": "Сияющий критический удар", "spellId": "445387", "pct": 0.3177083333333333}, {"slot": "Finger2", "name": "Сияющая универсальность", "spellId": "445349", "pct": 0.453125}, {"slot": "Finger2", "name": "Сияющий критический удар", "spellId": "445387", "pct": 0.28125}], "embellishmentPairs": {"11304,11304": 69, "11303,11303": 100, "11303,11304": 14, "11303,11941": 3, "10518,11304": 1, "11304,11941": 5}, "builds": [{"id": 0, "name": "Хаста/Верса", "pct": 46.9, "stats": {"crit": 18244, "haste": 24921, "mastery": 2942, "versatility": 19178}, "dist": {"crit": 28.2, "haste": 38.0, "mastery": 5.0, "versatility": 28.9}, "count": 90}, {"id": 1, "name": "Хаста/Крит", "pct": 29.7, "stats": {"crit": 21975, "haste": 22394, "mastery": 3273, "versatility": 17272}, "dist": {"crit": 34.0, "haste": 34.4, "mastery": 5.3, "versatility": 26.2}, "count": 57}, {"id": 2, "name": "Хаста/Крит", "pct": 23.4, "stats": {"crit": 18583, "haste": 23343, "mastery": 7057, "versatility": 17486}, "dist": {"crit": 28.3, "haste": 34.8, "mastery": 11.3, "versatility": 25.6}, "count": 45}], "segments": [{"tier": 0, "label": "Топ 25%", "count": 48, "stats": {"crit": 19160, "haste": 22920, "mastery": 3348, "versatility": 17928}}, {"tier": 1, "label": "25-50%", "count": 48, "stats": {"crit": 19954, "haste": 24342, "mastery": 4122, "versatility": 17494}}, {"tier": 2, "label": "50-75%", "count": 48, "stats": {"crit": 18682, "haste": 23636, "mastery": 4058, "versatility": 17640}}, {"tier": 3, "label": "75-100%", "count": 48, "stats": {"crit": 18953, "haste": 24140, "mastery": 4104, "versatility": 18026}}], "_meta": {"mode": "mplus", "class": "hunter", "spec": "bm", "encounter": 62287, "metric": "dps"}}