{"count": 188, "ilvl": {"min": 717.6, "max": 729.6, "avg": 728.0}, "avgStats": {"haste": 20783, "crit": 9036, "mastery": 12852, "versatility": 20553, "strength": 7771.0, "agility": 12004.0, "intellect": 147473.0, "stamina": 785535.0}, "primaryStat": "intellect", "statsSource": "gear_stats", "allSlots": {"head": [{"item": {"itemId": 237718, "itemName": "Эфемерная широкополая шляпа авгура", "iconName": "inv_helm_cloth_raidmageethereal_d_01", "quality": "epic", "itemLevel": 730, "bonusIds": ["1540", "6652", "10255", "10356", "12231", "12365", "12676", "13446"], "fullItemUrl": "https://www.wowhead.com/ru/item=237718?bonus=1540:6652:10255:10356:12231:12365:12676:13446&ilvl=730"}, "count": 115, "pct": 0.6117021276595744}, {"item": {"itemId": 238033, "itemName": "Литургическая шляпа Зейда", "iconName": "inv_helm_cloth_raidmageethereal_d_01", "quality": "epic", "itemLevel": 730, "bonusIds": ["1540", "10255", "10356", "10844", "12239", "12365", "13446"], "fullItemUrl": "https://www.wowhead.com/ru/item=238033?bonus=1540:10255:10356:10844:12239:12365:13446&ilvl=730"}, "count": 9, "pct": 0.047872340425531915}], "neck": [{"item": {"itemId": 237568, "itemName": "Хризалида разлученных душ", "iconName": "inv_112_raidtrinkets_necklace01_etherealnontechnologicalstyle_gold", "quality": "epic", "itemLevel": 730, "bonusIds": ["1540", "6652", "10255", "10356", "10396", "10879", "13446"], "fullItemUrl": "https://www.wowhead.com/ru/item=237568?bonus=1540:6652:10255:10356:10396:10879:13446&ilvl=730"}, "count": 98, "pct": 0.5212765957446809}, {"item": {"itemId": 185820, "itemName": "Кабошон рода Бесконечности", "iconName": "inv_7_0raid_necklace_02c", "quality": "epic", "itemLevel": 730, "bonusIds": ["6652", "10042", "10255", "10383", "10389", "10396", "10879", "13446"], "fullItemUrl": "https://www.wowhead.com/ru/item=185820?bonus=6652:10042:10255:10383:10389:10396:10879:13446&ilvl=730"}, "count": 13, "pct": 0.06914893617021277}], "shoulder": [{"item": {"itemId": 237716, "itemName": "Эфемерные сферы могущества авгура", "iconName": "inv_shoulder_cloth_raidmageethereal_d_01", "quality": "epic", "itemLevel": 730, "bonusIds": ["1540", "6652", "10255", "10356", "12233", "12675", "13446"], "fullItemUrl": "https://www.wowhead.com/ru/item=237716?bonus=1540:6652:10255:10356:12233:12675:13446&ilvl=730"}, "count": 128, "pct": 0.6808510638297872}, {"item": {"itemId": 237547, "itemName": "Наплечные манапушки", "iconName": "inv_shoulder_cloth_raidpriestethereal_d_01", "quality": "epic", "itemLevel": 730, "bonusIds": ["1540", "6652", "10255", "10356", "12239", "13446"], "fullItemUrl": "https://www.wowhead.com/ru/item=237547?bonus=1540:6652:10255:10356:12239:13446&ilvl=730"}, "count": 14, "pct": 0.07446808510638298}], "back": [{"item": {"itemId": 235499, "itemName": "Повязки реши", "iconName": "inv_cape_armor_etherealshawl_d_01", "quality": "epic", "itemLevel": 730, "bonusIds": ["9893", "12259", "12401"], "fullItemUrl": "https://www.wowhead.com/ru/item=235499?bonus=9893:12259:12401&ilvl=730"}, "count": 181, "pct": 0.9627659574468085}], "chest": [{"item": {"itemId": 237721, "itemName": "Эфемерное обмундирование авгура", "iconName": "inv_robe_cloth_raidmageethereal_d_01", "quality": "epic", "itemLevel": 730, "bonusIds": ["1540", "6652", "10255", "10356", "12229", "12676", "13446"], "fullItemUrl": "https://www.wowhead.com/ru/item=237721?bonus=1540:6652:10255:10356:12229:12676:13446&ilvl=730"}, "count": 150, "pct": 0.7978723404255319}, {"item": {"itemId": 237527, "itemName": "Одежды единения духа", "iconName": "inv_robe_cloth_raidwarlockethereal_d_01", "quality": "epic", "itemLevel": 730, "bonusIds": ["1540", "6652", "10255", "10356", "12239", "13446"], "fullItemUrl": "https://www.wowhead.com/ru/item=237527?bonus=1540:6652:10255:10356:12239:13446&ilvl=730"}, "count": 6, "pct": 0.031914893617021274}], "wrist": [{"item": {"itemId": 222815, "itemName": "Освященные манжеты", "iconName": "inv_cloth_outdoorarathor_d_01_bracer", "quality": "epic", "itemLevel": 727, "bonusIds": ["8792", "8902", "8960", "9627", "9633", "10421", "11304", "12050", "12053", "12922", "13468"], "fullItemUrl": "https://www.wowhead.com/ru/item=222815?bonus=8792:8902:8960:9627:9633:10421:11304:12050:12053:12922:13468&ilvl=727"}, "count": 105, "pct": 0.5585106382978723}], "hands": [{"item": {"itemId": 237719, "itemName": "Эфемерные полуперчатки авгура", "iconName": "inv_glove_cloth_raidmageethereal_d_01", "quality": "epic", "itemLevel": 730, "bonusIds": ["1540", "6652", "10255", "10356", "12230", "12675", "13446"], "fullItemUrl": "https://www.wowhead.com/ru/item=237719?bonus=1540:6652:10255:10356:12230:12675:13446&ilvl=730"}, "count": 125, "pct": 0.6648936170212766}, {"item": {"itemId": 222822, "itemName": "Освященные перчатки", "iconName": "inv_cloth_outdoorarathor_d_01_glove", "quality": "epic", "itemLevel": 727, "bonusIds": ["8792", "8902", "8960", "9627", "9633", "10421", "11304", "12050", "12053", "13468"], "fullItemUrl": "https://www.wowhead.com/ru/item=222822?bonus=8792:8902:8960:9627:9633:10421:11304:12050:12053:13468&ilvl=727"}, "count": 7, "pct": 0.03723404255319149}], "waist": [{"item": {"itemId": 222816, "itemName": "Освященный шнурованный ремень", "iconName": "inv_cloth_outdoorarathor_d_01_belt", "quality": "epic", "itemLevel": 727, "bonusIds": ["8792", "8902", "8960", "9627", "9633", "10421", "11304", "12050", "12053", "12922", "13468"], "fullItemUrl": "https://www.wowhead.com/ru/item=222816?bonus=8792:8902:8960:9627:9633:10421:11304:12050:12053:12922:13468&ilvl=727"}, "count": 85, "pct": 0.4521276595744681}, {"item": {"itemId": 237538, "itemName": "Книжный чехол ткача горна", "iconName": "inv_belt_cloth_raidwarlockethereal_d_01", "quality": "epic", "itemLevel": 730, "bonusIds": ["1540", "6652", "10255", "10356", "12239", "12365", "13446"], "fullItemUrl": "https://www.wowhead.com/ru/item=237538?bonus=1540:6652:10255:10356:12239:12365:13446&ilvl=730"}, "count": 17, "pct": 0.09042553191489362}], "legs": [{"item": {"itemId": 237717, "itemName": "Эфемерные штаны авгура", "iconName": "inv_pant_cloth_raidmageethereal_d_01", "quality": "epic", "itemLevel": 730, "bonusIds": ["1540", "6652", "10255", "10390", "12232", "12676", "13446"], "fullItemUrl": "https://www.wowhead.com/ru/item=237717?bonus=1540:6652:10255:10390:12232:12676:13446&ilvl=730"}, "count": 139, "pct": 0.7393617021276596}], "feet": [{"item": {"itemId": 243305, "itemName": "Шелковые походные сапоги захватчика", "iconName": "inv_boot_cloth_raidpriestethereal_d_01", "quality": "epic", "itemLevel": 730, "bonusIds": ["1540", "6652", "10255", "10356", "12239", "13446", "13504"], "fullItemUrl": "https://www.wowhead.com/ru/item=243305?bonus=1540:6652:10255:10356:12239:13446:13504&ilvl=730"}, "count": 160, "pct": 0.851063829787234}], "finger1": [{"item": {"itemId": 215135, "itemName": "Кольцо мастерства земельников", "iconName": "inv_11_0_earthen_earthenring_color1", "quality": "epic", "itemLevel": 727, "bonusIds": ["8795", "8902", "9627", "9633", "10396", "10421", "10879", "12050", "12053", "13468"], "fullItemUrl": "https://www.wowhead.com/ru/item=215135?bonus=8795:8902:9627:9633:10396:10421:10879:12050:12053:13468&ilvl=727"}, "count": 25, "pct": 0.13297872340425532}, {"item": {"itemId": 242405, "itemName": "Перстень расколотой души", "iconName": "inv_112_raidtrinkets_ring02_etherealribbonorrunestyle_gold", "quality": "epic", "itemLevel": 730, "bonusIds": ["1540", "6652", "10255", "10356", "10396", "10879", "13446"], "fullItemUrl": "https://www.wowhead.com/ru/item=242405?bonus=1540:6652:10255:10356:10396:10879:13446&ilvl=730"}, "count": 12, "pct": 0.06382978723404255}], "finger2": [{"item": {"itemId": 215135, "itemName": "Кольцо мастерства земельников", "iconName": "inv_11_0_earthen_earthenring_color1", "quality": "epic", "itemLevel": 727, "bonusIds": ["8792", "8902", "9627", "9633", "10396", "10421", "10879", "12050", "12053", "13468"], "fullItemUrl": "https://www.wowhead.com/ru/item=215135?bonus=8792:8902:9627:9633:10396:10421:10879:12050:12053:13468&ilvl=727"}, "count": 16, "pct": 0.0851063829787234}, {"item": {"itemId": 221141, "itemName": "Печатка высшего неруба", "iconName": "inv_11_0_nerubian_ring_02_color5", "quality": "epic", "itemLevel": 730, "bonusIds": ["3222", "6652", "10255", "10383", "10390", "10396", "10879", "13446"], "fullItemUrl": "https://www.wowhead.com/ru/item=221141?bonus=3222:6652:10255:10383:10390:10396:10879:13446&ilvl=730"}, "count": 10, "pct": 0.05319148936170213}]}, "weapon": [{"item": {"itemId": 237730, "itemName": "Шпиль из стекла Бездны", "iconName": "inv_staff_2h_etherealraid_d_02", "quality": "epic", "itemLevel": 730, "bonusIds": ["1540", "6652", "10255", "10356", "13446"], "fullItemUrl": "https://www.wowhead.com/ru/item=237730?bonus=1540:6652:10255:10356:13446&ilvl=730"}, "count": 93, "pct": 0.4946808510638298}, {"item": {"itemId": 237728, "itemName": "Крис из стекла бездны", "iconName": "inv_knife_1h_etherealraid_d_02", "quality": "epic", "itemLevel": 730, "bonusIds": ["1540", "6652", "10255", "10356", "13446"], "fullItemUrl": "https://www.wowhead.com/ru/item=237728?bonus=1540:6652:10255:10356:13446&ilvl=730"}, "count": 67, "pct": 0.35638297872340424}, {"item": {"itemId": 237735, "itemName": "Клинок властителя из стекла Бездны", "iconName": "inv_sword_1h_etherealraid_d_01", "quality": "epic", "itemLevel": 730, "bonusIds": ["1540", "6652", "10255", "10356", "13446"], "fullItemUrl": "https://www.wowhead.com/ru/item=237735?bonus=1540:6652:10255:10356:13446&ilvl=730"}, "count": 13, "pct": 0.06914893617021277}, {"item": {"itemId": 185822, "itemName": "Посох расколотого континуума", "iconName": "inv_staff_2h_broker_c_01", "quality": "epic", "itemLevel": 730, "bonusIds": ["6652", "10042", "10255", "10384", "10389", "13446"], "fullItemUrl": "https://www.wowhead.com/ru/item=185822?bonus=6652:10042:10255:10384:10389:13446&ilvl=730"}, "count": 3, "pct": 0.015957446808510637}], "offHand": [{"item": {"itemId": 222566, "itemName": "Факел бродяги", "iconName": "inv_offhand_1h_arathoroutdoor_d_01", "quality": "epic", "itemLevel": 727, "bonusIds": ["8792", "8902", "8960", "9627", "9633", "10421", "11300", "12050", "12053", "13468"], "fullItemUrl": "https://www.wowhead.com/ru/item=222566?bonus=8792:8902:8960:9627:9633:10421:11300:12050:12053:13468&ilvl=727"}, "count": 29, "pct": 0.15425531914893617}, {"item": {"itemId": 237724, "itemName": "Радуга запредельной тьмы", "iconName": "inv_offhand_1h_etherealraid_d_01", "quality": "epic", "itemLevel": 730, "bonusIds": ["1540", "6652", "10255", "10356", "13446"], "fullItemUrl": "https://www.wowhead.com/ru/item=237724?bonus=1540:6652:10255:10356:13446&ilvl=730"}, "count": 21, "pct": 0.11170212765957446}, {"item": {"itemId": 237742, "itemName": "Последний вздох Разломия", "iconName": "inv_offhand_1h_etherealraid_d_02", "quality": "epic", "itemLevel": 730, "bonusIds": ["1540", "6652", "10255", "10356", "13446"], "fullItemUrl": "https://www.wowhead.com/ru/item=237742?bonus=1540:6652:10255:10356:13446&ilvl=730"}, "count": 15, "pct": 0.0797872340425532}, {"item": {"itemId": 185812, "itemName": "Услаждающая слух кадильница", "iconName": "inv_offhand_1h_broker_c_01", "quality": "epic", "itemLevel": 730, "bonusIds": ["6652", "10042", "10255", "10383", "10389", "13446"], "fullItemUrl": "https://www.wowhead.com/ru/item=185812?bonus=6652:10042:10255:10383:10389:13446&ilvl=730"}, "count": 12, "pct": 0.06382978723404255}, {"item": {"itemId": 221132, "itemName": "Переполненная тьмой кадка", "iconName": "inv_offhand_1h_earthendungeon_c_01", "quality": "epic", "itemLevel": 730, "bonusIds": ["3222", "6652", "10255", "10383", "10390", "13446"], "fullItemUrl": "https://www.wowhead.com/ru/item=221132?bonus=3222:6652:10255:10383:10390:13446&ilvl=730"}, "count": 4, "pct": 0.02127659574468085}], "trinkets": [{"item": {"itemId": 242392, "itemName": "Алмазный сердечник Бездны", "iconName": "inv_112_raidtrinkets_intdps_ancientkareshirelic", "quality": "epic", "itemLevel": 730, "bonusIds": ["1540", "6652", "10255", "10356", "13446"], "fullItemUrl": "https://www.wowhead.com/ru/item=242392?bonus=1540:6652:10255:10356:13446&ilvl=730"}, "count": 163, "pct": 0.8670212765957447}, {"item": {"itemId": 242395, "itemName": "Астральный усик", "iconName": "inv_112_raidtrinkets_silkwormsantenna", "quality": "epic", "itemLevel": 730, "bonusIds": ["1540", "6652", "10255", "10356", "13446"], "fullItemUrl": "https://www.wowhead.com/ru/item=242395?bonus=1540:6652:10255:10356:13446&ilvl=730"}, "count": 159, "pct": 0.8457446808510638}, {"item": {"itemId": 242497, "itemName": "Параподии Ажиккара", "iconName": "inv_devourersmallmount_light", "quality": "epic", "itemLevel": 730, "bonusIds": ["3222", "6652", "10255", "10383", "10390", "13446"], "fullItemUrl": "https://www.wowhead.com/ru/item=242497?bonus=3222:6652:10255:10383:10390:13446&ilvl=730"}, "count": 46, "pct": 0.24468085106382978}, {"item": {"itemId": 219314, "itemName": "Кокон выводка Ара-Кары", "iconName": "inv_raid_mercurialegg_red", "quality": "epic", "itemLevel": 730, "bonusIds": ["3222", "6652", "10255", "10383", "10390", "13446"], "fullItemUrl": "https://www.wowhead.com/ru/item=219314?bonus=3222:6652:10255:10383:10390:13446&ilvl=730"}, "count": 2, "pct": 0.010638297872340425}, {"item": {"itemId": 242494, "itemName": "Лилия вечного плетения", "iconName": "inv_herb_karesh", "quality": "epic", "itemLevel": 730, "bonusIds": ["3222", "6652", "10255", "10383", "10390", "13446"], "fullItemUrl": "https://www.wowhead.com/ru/item=242494?bonus=3222:6652:10255:10383:10390:13446&ilvl=730"}, "count": 2, "pct": 0.010638297872340425}, {"item": {"itemId": 242402, "itemName": "Ритуальный горн Араза", "iconName": "inv_112_raidtrinkets_trinkettechnomancer_ritualengine", "quality": "epic", "itemLevel": 730, "bonusIds": ["1540", "6652", "10255", "10356", "13446"], "fullItemUrl": "https://www.wowhead.com/ru/item=242402?bonus=1540:6652:10255:10356:13446&ilvl=730"}, "count": 2, "pct": 0.010638297872340425}, {"item": {"itemId": 219312, "itemName": "Усиливающий кристалл Ануб'иккаджа", "iconName": "inv_arathordungeon_fragment_color5", "quality": "epic", "itemLevel": 730, "bonusIds": ["3222", "6652", "10255", "10383", "10390", "13446"], "fullItemUrl": "https://www.wowhead.com/ru/item=219312?bonus=3222:6652:10255:10383:10390:13446&ilvl=730"}, "count": 1, "pct": 0.005319148936170213}, {"item": {"itemId": 190958, "itemName": "Тайный прием Со'леи", "iconName": "inv_60pvp_trinket1d", "quality": "epic", "itemLevel": 730, "bonusIds": ["6652", "10042", "10255", "10383", "10390", "13446"], "fullItemUrl": "https://www.wowhead.com/ru/item=190958?bonus=6652:10042:10255:10383:10390:13446&ilvl=730"}, "count": 1, "pct": 0.005319148936170213}], "tierStats": [{"slot": "Ноги", "slotKey": "legs", "pct": 0.9468085106382979, "item": {"itemId": 237717, "itemName": "Эфемерные штаны авгура", "iconName": "inv_pant_cloth_raidmageethereal_d_01", "quality": "epic", "itemLevel": 730, "bonusIds": ["1540", "6652", "10255", "10390", "12232", "12676", "13446"], "fullItemUrl": "https://www.wowhead.com/ru/item=237717?bonus=1540:6652:10255:10390:12232:12676:13446&ilvl=730"}}, {"slot": "Грудь", "slotKey": "chest", "pct": 0.9148936170212766, "item": {"itemId": 237721, "itemName": "Эфемерное обмундирование авгура", "iconName": "inv_robe_cloth_raidmageethereal_d_01", "quality": "epic", "itemLevel": 730, "bonusIds": ["1540", "6652", "10255", "10356", "12229", "12676", "13446"], "fullItemUrl": "https://www.wowhead.com/ru/item=237721?bonus=1540:6652:10255:10356:12229:12676:13446&ilvl=730"}}, {"slot": "Голова", "slotKey": "head", "pct": 0.8351063829787234, "item": {"itemId": 237718, "itemName": "Эфемерная широкополая шляпа авгура", "iconName": "inv_helm_cloth_raidmageethereal_d_01", "quality": "epic", "itemLevel": 730, "bonusIds": ["1540", "6652", "10255", "10356", "12231", "12365", "12676", "13446"], "fullItemUrl": "https://www.wowhead.com/ru/item=237718?bonus=1540:6652:10255:10356:12231:12365:12676:13446&ilvl=730"}}, {"slot": "Плечи", "slotKey": "shoulder", "pct": 0.824468085106383, "item": {"itemId": 237716, "itemName": "Эфемерные сферы могущества авгура", "iconName": "inv_shoulder_cloth_raidmageethereal_d_01", "quality": "epic", "itemLevel": 730, "bonusIds": ["1540", "6652", "10255", "10356", "12233", "12675", "13446"], "fullItemUrl": "https://www.wowhead.com/ru/item=237716?bonus=1540:6652:10255:10356:12233:12675:13446&ilvl=730"}}, {"slot": "Руки", "slotKey": "hands", "pct": 0.8031914893617021, "item": {"itemId": 237719, "itemName": "Эфемерные полуперчатки авгура", "iconName": "inv_glove_cloth_raidmageethereal_d_01", "quality": "epic", "itemLevel": 730, "bonusIds": ["1540", "6652", "10255", "10356", "12230", "12675", "13446"], "fullItemUrl": "https://www.wowhead.com/ru/item=237719?bonus=1540:6652:10255:10356:12230:12675:13446&ilvl=730"}}], "enchants": [{"slot": "Back", "name": "Песнь крылатой грации", "spellId": "445386", "pct": 0.9361702127659575}, {"slot": "Back", "name": "Песнь клыков и самоисцеления", "spellId": "445393", "pct": 0.03723404255319149}, {"slot": "Chest", "name": "Кристаллическое сияние", "spellId": "445333", "pct": 0.9787234042553191}, {"slot": "Chest", "name": "Enchant 445322", "spellId": "445322", "pct": 0.02127659574468085}, {"slot": "Wrist", "name": "Песнь брони и избежания", "spellId": "445334", "pct": 0.9627659574468085}, {"slot": "Wrist", "name": "Песнь брони и самоисцеления", "spellId": "445325", "pct": 0.02127659574468085}, {"slot": "Legs", "name": "Enchant 457620", "spellId": "457620", "pct": 0.7340425531914894}, {"slot": "Legs", "name": "Enchant 457623", "spellId": "457623", "pct": 0.26063829787234044}, {"slot": "Feet", "name": "Ход защитника", "spellId": "445396", "pct": 0.8351063829787234}, {"slot": "Feet", "name": "Ход разведчика", "spellId": "445368", "pct": 0.16489361702127658}, {"slot": "Main_hand", "name": "Упорство Присягнувших", "spellId": "445351", "pct": 0.8882978723404256}, {"slot": "Main_hand", "name": "Хитрость Совета", "spellId": "445379", "pct": 0.05851063829787234}, {"slot": "Finger1", "name": "Сияющая универсальность", "spellId": "445349", "pct": 0.4946808510638298}, {"slot": "Finger1", "name": "Сияющая скорость", "spellId": "445320", "pct": 0.2393617021276596}, {"slot": "Finger2", "name": "Сияющая универсальность", "spellId": "445349", "pct": 0.48404255319148937}, {"slot": "Finger2", "name": "Сияющая скорость", "spellId": "445320", "pct": 0.22872340425531915}], "embellishmentPairs": {"11304,11304": 132, "11109,11300": 29, "10520,11304": 6, "11304,11941": 9, "10520,11303": 1, "11303,11303": 6, "11303,11304": 3, "10520,11300": 1, "11303,11941": 1}, "builds": [{"id": 0, "name": "Хаста/Верса", "pct": 53.2, "stats": {"crit": 7770, "haste": 20832, "mastery": 15104, "versatility": 20260}, "dist": {"crit": 11.8, "haste": 32.8, "mastery": 23.6, "versatility": 31.8}, "count": 100}, {"id": 1, "name": "Верса/Хаста", "pct": 46.8, "stats": {"crit": 10284, "haste": 20422, "mastery": 10608, "versatility": 21512}, "dist": {"crit": 16.6, "haste": 32.9, "mastery": 16.7, "versatility": 33.8}, "count": 88}], "segments": [{"tier": 0, "label": "Топ 25%", "count": 47, "stats": {"crit": 9450, "haste": 20799, "mastery": 12507, "versatility": 20253}}, {"tier": 1, "label": "25-50%", "count": 47, "stats": {"crit": 9209, "haste": 21372, "mastery": 12469, "versatility": 20324}}, {"tier": 2, "label": "50-75%", "count": 47, "stats": {"crit": 8152, "haste": 20360, "mastery": 12747, "versatility": 21182}}, {"tier": 3, "label": "75-100%", "count": 47, "stats": {"crit": 8175, "haste": 20204, "mastery": 13369, "versatility": 20924}}], "_meta": {"mode": "mplus", "class": "mage", "spec": "arcane", "encounter": 12830, "metric": "dps"}}